bloqade/pyqrack/__init__.py
bloqade/pyqrack/base.py
bloqade/pyqrack/reg.py
bloqade/pyqrack/target.py
bloqade/pyqrack/noise/__init__.py
bloqade/pyqrack/noise/native.py
bloqade/pyqrack/qasm2/__init__.py
bloqade/pyqrack/qasm2/core.py
bloqade/pyqrack/qasm2/parallel.py
bloqade/pyqrack/qasm2/uop.py
bloqade_pyqrack-0.5.0.dist-info/METADATA
bloqade_pyqrack-0.5.0.dist-info/WHEEL
bloqade_pyqrack-0.5.0.dist-info/licenses/LICENSE
bloqade_pyqrack-0.5.0.dist-info/RECORD
