Metadata-Version: 2.4
Name: bloqade-pyqrack
Version: 0.5.0
Summary: Runtime for bloqade using the Qrack simulator.
Author-email: Roger-luo <rluo@quera.com>, kaihsin <khwu@quera.com>, weinbe58 <pweinberg@quera.com>, johnzl-777 <jlong@quera.com>
License-File: LICENSE
Requires-Python: >=3.10
Requires-Dist: bloqade[qasm2]>=0.17.0
Requires-Dist: kirin-toolchain~=0.14.0
Provides-Extra: pyqrack
Requires-Dist: pyqrack>=1.36.1; extra == 'pyqrack'
Provides-Extra: pyqrack-cpu
Requires-Dist: pyqrack-cpu>=1.36.1; extra == 'pyqrack-cpu'
Provides-Extra: pyqrack-cuda
Requires-Dist: pyqrack-cuda>=1.36.1; extra == 'pyqrack-cuda'
